findmy/__init__.py
findmy/__main__.py
findmy/accessory.py
findmy/errors.py
findmy/keys.py
findmy/plist.py
findmy/reports/__init__.py
findmy/reports/account.py
findmy/reports/anisette.py
findmy/reports/reports.py
findmy/reports/state.py
findmy/reports/twofactor.py
findmy/scanner/__init__.py
findmy/scanner/scanner.py
findmy/util/__init__.py
findmy/util/abc.py
findmy/util/crypto.py
findmy/util/files.py
findmy/util/http.py
findmy/util/parsers.py
findmy/util/session.py
findmy/util/types.py
findmy-0.9.8.dist-info/licenses/LICENSE.md
findmy-0.9.8.dist-info/METADATA
findmy-0.9.8.dist-info/WHEEL
findmy-0.9.8.dist-info/top_level.txt
findmy-0.9.8.dist-info/RECORD
