Metadata-Version: 2.4
Name: FindMy
Version: 0.9.8
Summary: Query the location of your FindMy devices with Python!
Author-email: Mike Almeloo <git@mikealmel.ooo>
Requires-Python: <3.15,>=3.10
License-File: LICENSE.md
Requires-Dist: srp<2.0.0,>=1.0.21
Requires-Dist: cryptography<47.0.0,>=42.0.0
Requires-Dist: beautifulsoup4<5.0.0,>=4.12.3
Requires-Dist: aiohttp<4.0.0,>=3.9.5
Requires-Dist: bleak<3.0.0,>=2.0.0
Requires-Dist: typing-extensions<5.0.0,>=4.12.2
Requires-Dist: anisette<2.0.0,>=1.2.4
Dynamic: license-file
